_secure_random.cpython-311-x86_64-linux-gnu.so
sha256sr/__init__.py
sha256sr/secure_random.cpp
sha256sr/secure_random.h
sha256sr/secure_random.py
sha256sr/sha256.cpp
sha256sr/sha256.h
sha256sr/swig_wrap.cxx
sha256sr-0.1.9.dist-info/METADATA
sha256sr-0.1.9.dist-info/WHEEL
sha256sr-0.1.9.dist-info/top_level.txt
sha256sr-0.1.9.dist-info/RECORD
