Metadata-Version: 2.1
Name: sha256sr
Version: 0.1.9
Summary: the secure random generator based on SHA256
Home-page: UNKNOWN
Author: zhangdaode
Author-email: zhangdaode0119@gmail.com
License: UNKNOWN
Platform: UNKNOWN
Classifier: Programming Language :: Python :: 2
Classifier: Programming Language :: Python :: 2.7
Classifier: Programming Language :: Python :: 3
Classifier: Programming Language :: Python :: 3.4
Classifier: Programming Language :: Python :: 3.5
Classifier: Programming Language :: Python :: 3.6
Requires-Dist: setuptools (<=59.4.0,>=44.1.0)
